bibexcel/__init__.py
bibexcel/bibexcel.py
bibexcel-1.0.3.dist-info/LICENSE
bibexcel-1.0.3.dist-info/METADATA
bibexcel-1.0.3.dist-info/WHEEL
bibexcel-1.0.3.dist-info/top_level.txt
bibexcel-1.0.3.dist-info/RECORD
