Metadata-Version: 2.1
Name: bibexcel
Version: 1.0.3
Summary: A python executable to get JSON and Excel data from a bibexcel text file
Home-page: http://github.com/storopoli/bibexcel
Author: Jose Eduardo Storopoli
Author-email: thestoropoli@gmail.com
License: MIT
Platform: UNKNOWN
Classifier: Programming Language :: Python :: 3
Classifier: License :: OSI Approved :: MIT License
Classifier: Operating System :: OS Independent
Requires-Python: >=3.6
Requires-Dist: pandas
